pipelineer/__init__.py
pipelineer/cli.py
pipelineer/templates/api.py
pipelineer/templates/oracle.py
pipelineer/utils/__init__.py
pipelineer/utils/generator.py
pipelineer/utils/mappers.py
pipelineer/utils/templates.py
pipelineer-1.5.8.dist-info/METADATA
pipelineer-1.5.8.dist-info/WHEEL
pipelineer-1.5.8.dist-info/entry_points.txt
pipelineer-1.5.8.dist-info/top_level.txt
pipelineer-1.5.8.dist-info/RECORD
