Metadata-Version: 2.1
Name: pipelineer
Version: 1.5.8
Summary: "Herramienta para generar esquemas Avro, JSON y SQL desde definiciones Oracle."
Author: "Sebastian Aguilar"
Author-email: "sebastian.aguilar.sanhueza@gmail.com"
License: "MIT"
Classifier: Programming Language :: Python :: 3
Classifier: License :: OSI Approved :: MIT License
Classifier: Operating System :: OS Independent
Requires-Python: >=3.9
